examples/__init__.py
examples/ex_sim.py
examples/ex_toy.py
glm_lib/__init__.py
glm_lib/distns.py
glm_lib/models.py
glm_lib-0.0.1.dist-info/LICENSE.md
glm_lib-0.0.1.dist-info/METADATA
glm_lib-0.0.1.dist-info/WHEEL
glm_lib-0.0.1.dist-info/top_level.txt
glm_lib-0.0.1.dist-info/RECORD
