Metadata-Version: 2.1
Name: glm-lib
Version: 0.0.1
Summary: Lightweight Python library for Generalized Linear Models.
Home-page: https://github.com/tonyduan/glm-lib
Author: Tony Duan
Author-email: tonyduan@cs.stanford.edu
License: UNKNOWN
Platform: UNKNOWN
Classifier: Programming Language :: Python :: 3
Classifier: License :: OSI Approved :: MIT License
Classifier: Operating System :: OS Independent
